README.rst
setup.py
pydriveV3/__init__.py
pydriveV3/authorize.py
pydriveV3/constants.py
pydriveV3/decorator.py
pydriveV3/drive3client.py
pydriveV3/exceptions.py
pydriveV3.egg-info/PKG-INFO
pydriveV3.egg-info/SOURCES.txt
pydriveV3.egg-info/dependency_links.txt
pydriveV3.egg-info/requires.txt
pydriveV3.egg-info/top_level.txt