Metadata-Version: 1.0
Name: pydriveV3
Version: 0.1.2
Summary: A package that wrap over the google drive v3 apis
Home-page: https://github.com/Afsalms/pydrive3
Author: AfsalSalim
Author-email: afsalms93.mec@gmail.com
License: UNKNOWN
Platform: UNKNOWN
